Verilog/memory.v
module memory(
    input wire [3:0] addr,             // Memory address
    input wire [7:0] data_in,             // Memory data in
    output reg [7:0] data_out,             // Memory data out
    input wire write,                  // Write enable signal
    input wire read,                   // Read enable signal
    input wire rst_n,                 // Active low reset signal
    input wire clk                       // Clock signal
);

reg [7:0] mem [0:255]; // Memory array (256 bytes)
integer i;

always @(posedge clk) begin
    if (!rst_n) begin
        // Initialize memory to zero on reset
        for (i = 0; i < 256; i = i + 1) begin
            mem[i] <= 8'b0;
        end
    end else if (read && !write) begin
        data_out <= mem[addr]; // Read data from memory
    end else
    if (write) begin
        mem[addr] <= data_in; // Write data to memory
    end
end

endmodule

Verilog/tb/memory_tb.v
`timescale 1ns / 1ps

module memory_tb;

    // Parameters
    parameter DATA_WIDTH = 8;
    parameter ADDR_WIDTH = 4;
    
    // Inputs
    reg [ADDR_WIDTH-1:0] address;
    reg [DATA_WIDTH-1:0] data;
    reg write_enable;
    reg read_enable;
    
    // Outputs
    wire [DATA_WIDTH-1:0] data_out;
    
    // Testbench signals
    reg clk;
    reg rst_n;
    integer i;

    // Instantiate memory module
    memory dut (
        .addr(address), 
        .data_in(data),
        .data_out(data_out),
        .write(write_enable),
        .read(read_enable),
        .rst_n(rst_n),
        .clk(clk)
    );

    // Clock generation
    initial begin
        $dumpfile("waveforms/memory.vcd");
        $dumpvars(0, memory_tb);
        $monitor("Time: %0t | clk: %b | rst_n: %b | address: %h | data_in: %h | write_enable: %b | read_enable: %b | data_out: %h",
                 $time, clk, rst_n, address, data, write_enable, read_enable, data_out);
        clk = 0;
        forever #5 clk = ~clk; // 10 ns clock period
    end

    // Stimulus
    initial begin
        rst_n = 0;
        address = 0;
        data = 0;
        write_enable = 0;
        read_enable = 0;
        #10;
        rst_n = 1;
        #10;

        // Test write operation
        for (i = 0; i < 16; i = i + 1) begin
            address = i; // Address to write to
            data = i * 2; // Write some data
            write_enable = 1;
            read_enable = 0;
            #10;
            write_enable = 0;
            #10;
        end

        // Test read operation
        for (i = 0; i < 16; i = i + 1) begin
            address = i; // Address to read from
            write_enable = 0;
            read_enable = 1;
            #10;
            read_enable = 0;
            #10;
        end

        // Test reset operation
        rst_n = 0;
        #10;
        rst_n = 1;
        #10;

        // Test read after reset
        for (i = 0; i < 16; i = i + 1) begin
            address = i; // Address to read from
            write_enable = 0;
            read_enable = 1;
            #10;
            read_enable = 0;
            #10;
        end

        // Finish simulation
        $finish;
    end

endmodule

Verilog/waveforms/memory.vcd
$date
	Wed May 21 23:26:02 2025
$end
$version
	Icarus Verilog
$end
$timescale
	1ps
$end
$scope module memory_tb $end
$var wire 8 ! data_out [7:0] $end
$var parameter 32 " ADDR_WIDTH $end
$var parameter 32 # DATA_WIDTH $end
$var reg 4 $ address [3:0] $end
$var reg 1 % clk $end
$var reg 8 & data [7:0] $end
$var reg 1 ' read_enable $end
$var reg 1 ( rst_n $end
$var reg 1 ) write_enable $end
$var integer 32 * i [31:0] $end
$scope module dut $end
$var wire 4 + addr [3:0] $end
$var wire 1 % clk $end
$var wire 8 , data_in [7:0] $end
$var wire 1 ' read $end
$var wire 1 ( rst_n $end
$var wire 1 ) write $end
$var reg 8 - data_out [7:0] $end
$var integer 32 . i [31:0] $end
$upscope $end
$upscope $end
$enddefinitions $end
$comment Show the parameter values. $end
$dumpall
b1000 #
b100 "
$end
#0
$dumpvars
bx .
bx -
b0 ,
b0 +
bx *
0)
0(
0'
b0 &
0%
b0 $
bx !
$end
#5000
b100000000 .
1%
#10000
0%
1(
#15000
1%
#20000
0%
1)
b0 *
#25000
1%
#30000
0%
0)
#35000
1%
#40000
0%
1)
b10 &
b10 ,
b1 $
b1 +
b1 *
#45000
1%
#50000
0%
0)
#55000
1%
#60000
0%
1)
b100 &
b100 ,
b10 $
b10 +
b10 *
#65000
1%
#70000
0%
0)
#75000
1%
#80000
0%
1)
b110 &
b110 ,
b11 $
b11 +
b11 *
#85000
1%
#90000
0%
0)
#95000
1%
#100000
0%
1)
b1000 &
b1000 ,
b100 $
b100 +
b100 *
#105000
1%
#110000
0%
0)
#115000
1%
#120000
0%
1)
b1010 &
b1010 ,
b101 $
b101 +
b101 *
#125000
1%
#130000
0%
0)
#135000
1%
#140000
0%
1)
b1100 &
b1100 ,
b110 $
b110 +
b110 *
#145000
1%
#150000
0%
0)
#155000
1%
#160000
0%
1)
b1110 &
b1110 ,
b111 $
b111 +
b111 *
#165000
1%
#170000
0%
0)
#175000
1%
#180000
0%
1)
b10000 &
b10000 ,
b1000 $
b1000 +
b1000 *
#185000
1%
#190000
0%
0)
#195000
1%
#200000
0%
1)
b10010 &
b10010 ,
b1001 $
b1001 +
b1001 *
#205000
1%
#210000
0%
0)
#215000
1%
#220000
0%
1)
b10100 &
b10100 ,
b1010 $
b1010 +
b1010 *
#225000
1%
#230000
0%
0)
#235000
1%
#240000
0%
1)
b10110 &
b10110 ,
b1011 $
b1011 +
b1011 *
#245000
1%
#250000
0%
0)
#255000
1%
#260000
0%
1)
b11000 &
b11000 ,
b1100 $
b1100 +
b1100 *
#265000
1%
#270000
0%
0)
#275000
1%
#280000
0%
1)
b11010 &
b11010 ,
b1101 $
b1101 +
b1101 *
#285000
1%
#290000
0%
0)
#295000
1%
#300000
0%
1)
b11100 &
b11100 ,
b1110 $
b1110 +
b1110 *
#305000
1%
#310000
0%
0)
#315000
1%
#320000
0%
1)
b11110 &
b11110 ,
b1111 $
b1111 +
b1111 *
#325000
1%
#330000
0%
0)
#335000
1%
#340000
0%
1'
b0 $
b0 +
b0 *
#345000
b0 !
b0 -
1%
#350000
0%
0'
#355000
1%
#360000
0%
1'
b1 $
b1 +
b1 *
#365000
b10 !
b10 -
1%
#370000
0%
0'
#375000
1%
#380000
0%
1'
b10 $
b10 +
b10 *
#385000
b100 !
b100 -
1%
#390000
0%
0'
#395000
1%
#400000
0%
1'
b11 $
b11 +
b11 *
#405000
b110 !
b110 -
1%
#410000
0%
0'
#415000
1%
#420000
0%
1'
b100 $
b100 +
b100 *
#425000
b1000 !
b1000 -
1%
#430000
0%
0'
#435000
1%
#440000
0%
1'
b101 $
b101 +
b101 *
#445000
b1010 !
b1010 -
1%
#450000
0%
0'
#455000
1%
#460000
0%
1'
b110 $
b110 +
b110 *
#465000
b1100 !
b1100 -
1%
#470000
0%
0'
#475000
1%
#480000
0%
1'
b111 $
b111 +
b111 *
#485000
b1110 !
b1110 -
1%
#490000
0%
0'
#495000
1%
#500000
0%
1'
b1000 $
b1000 +
b1000 *
#505000
b10000 !
b10000 -
1%
#510000
0%
0'
#515000
1%
#520000
0%
1'
b1001 $
b1001 +
b1001 *
#525000
b10010 !
b10010 -
1%
#530000
0%
0'
#535000
1%
#540000
0%
1'
b1010 $
b1010 +
b1010 *
#545000
b10100 !
b10100 -
1%
#550000
0%
0'
#555000
1%
#560000
0%
1'
b1011 $
b1011 +
b1011 *
#565000
b10110 !
b10110 -
1%
#570000
0%
0'
#575000
1%
#580000
0%
1'
b1100 $
b1100 +
b1100 *
#585000
b11000 !
b11000 -
1%
#590000
0%
0'
#595000
1%
#600000
0%
1'
b1101 $
b1101 +
b1101 *
#605000
b11010 !
b11010 -
1%
#610000
0%
0'
#615000
1%
#620000
0%
1'
b1110 $
b1110 +
b1110 *
#625000
b11100 !
b11100 -
1%
#630000
0%
0'
#635000
1%
#640000
0%
1'
b1111 $
b1111 +
b1111 *
#645000
b11110 !
b11110 -
1%
#650000
0%
0'
#655000
1%
#660000
0%
0(
b10000 *
#665000
b100000000 .
1%
#670000
0%
1(
#675000
1%
#680000
0%
1'
b0 $
b0 +
b0 *
#685000
b0 !
b0 -
1%
#690000
0%
0'
#695000
1%
#700000
0%
1'
b1 $
b1 +
b1 *
#705000
1%
#710000
0%
0'
#715000
1%
#720000
0%
1'
b10 $
b10 +
b10 *
#725000
1%
#730000
0%
0'
#735000
1%
#740000
0%
1'
b11 $
b11 +
b11 *
#745000
1%
#750000
0%
0'
#755000
1%
#760000
0%
1'
b100 $
b100 +
b100 *
#765000
1%
#770000
0%
0'
#775000
1%
#780000
0%
1'
b101 $
b101 +
b101 *
#785000
1%
#790000
0%
0'
#795000
1%
#800000
0%
1'
b110 $
b110 +
b110 *
#805000
1%
#810000
0%
0'
#815000
1%
#820000
0%
1'
b111 $
b111 +
b111 *
#825000
1%
#830000
0%
0'
#835000
1%
#840000
0%
1'
b1000 $
b1000 +
b1000 *
#845000
1%
#850000
0%
0'
#855000
1%
#860000
0%
1'
b1001 $
b1001 +
b1001 *
#865000
1%
#870000
0%
0'
#875000
1%
#880000
0%
1'
b1010 $
b1010 +
b1010 *
#885000
1%
#890000
0%
0'
#895000
1%
#900000
0%
1'
b1011 $
b1011 +
b1011 *
#905000
1%
#910000
0%
0'
#915000
1%
#920000
0%
1'
b1100 $
b1100 +
b1100 *
#925000
1%
#930000
0%
0'
#935000
1%
#940000
0%
1'
b1101 $
b1101 +
b1101 *
#945000
1%
#950000
0%
0'
#955000
1%
#960000
0%
1'
b1110 $
b1110 +
b1110 *
#965000
1%
#970000
0%
0'
#975000
1%
#980000
0%
1'
b1111 $
b1111 +
b1111 *
#985000
1%
#990000
0%
0'
#995000
1%
#1000000
0%
b10000 *
