Verilog/src/radio.v
module radio(
    input  wire        clk,         // Clock signal
    input  wire        enable,      // Enable signal
    // Control signals
    input  wire        send,        // Control signal from controller to trigger transmit
    output wire        busy,        // Indicates if the radio is busy
    input  wire        receive,     // Control signal from controller to trigger receive
    // Data transfer between controller and radio
    input  wire [7:0]  tx_data,     // Data from controller to transmit
    output reg [7:0]   rx_data,     // Data received, to controller
    // Radio signals
    output reg         Tx,          // Output signal (to antenna)
    input  wire        Rx          // Input signal (from antenna)

);

    // Transmit state
    reg [2:0] tx_bit_cnt = 0;
    reg [7:0] tx_shift_reg = 0;
    reg       tx_busy = 0;

    // Receive state
    reg [2:0] rx_bit_cnt = 0;
    reg [7:0] rx_shift_reg = 0;
    reg       rx_busy = 0;

    // Assign busy signal based on transmit and receive states
    assign busy = tx_busy || rx_busy;

    always @(posedge clk) begin
        if (!enable) begin
            // Reset everything if not enabled
            Tx <= 0;
            tx_bit_cnt <= 0;
            tx_shift_reg <= 0;
            tx_busy <= 0;
            rx_bit_cnt <= 0;
            rx_shift_reg <= 0;
            rx_busy <= 0;
            rx_data <= 8'b0;
        end else begin
            // TRANSMIT LOGIC
            if (send && !tx_busy) begin
                // Start transmission
                tx_shift_reg <= tx_data;
                tx_bit_cnt <= 0;
                tx_busy <= 1;
            end

            if (tx_busy) begin
                Tx <= tx_shift_reg[0]; // Send LSB first
                tx_shift_reg <= {1'b0, tx_shift_reg[7:1]}; // Shift right
                tx_bit_cnt <= tx_bit_cnt + 1;
                if (tx_bit_cnt == 7) begin
                    tx_busy <= 0; // Done transmitting 8 bits
                end
            end else begin
                Tx <= 0;
            end

            // RECEIVE LOGIC
            // Simple: sample Rx on every clock when enabled
            if (receive && !rx_busy) begin
                rx_busy <= 1;
                rx_bit_cnt <= 0;
                rx_shift_reg <= 0;
            end

            if (rx_busy) begin
                rx_shift_reg <= {Rx, rx_shift_reg[7:1]}; // Shift in Rx
                rx_bit_cnt <= rx_bit_cnt + 1;
                if (rx_bit_cnt == 7) begin
                    rx_data <= rx_shift_reg;
                    rx_busy <= 0;
                end
            end
        end
    end

endmodule

Verilog/radio_tb.v
`timescale 1ns/1ps

module radio_tb;

    reg clk = 0;
    reg enable = 0;
    reg send = 0;
    reg receive = 0;
    reg [7:0] tx_data = 8'b0;
    wire busy;
    wire [7:0] rx_data;
    wire Tx;
    reg Rx = 0;

    // Instantiate the radio module
    radio uut (
        .clk(clk),
        .enable(enable),
        .send(send),
        .busy(busy),
        .receive(receive),
        .tx_data(tx_data),
        .rx_data(rx_data),
        .Tx(Tx),
        .Rx(Rx)
    );

    // Clock generation
    always #5 clk = ~clk; // 100 MHz clock

    initial begin
        // Dumpfile setup for waveform viewing
        $dumpfile("waveforms/radio.vcd");
        $dumpvars(0, radio_tb);
        $monitor("Time: %0t | clk: %b | enable: %b | send: %b | receive: %b | tx_data: %b | busy: %b | Tx: %b | Rx: %b | rx_data: %b",
                 $time, clk, enable, send, receive, tx_data, busy, Tx, Rx, rx_data);

        // Initialize
        enable = 0;
        #10;
        enable = 1;
        send = 0;
        receive = 0;
        tx_data = 8'b10101010;
        Rx = 0;

        // Wait for a few cycles
        #20;

        // Test transmit
        send = 1;
        #10;
        send = 0;

        // Wait for transmission to finish
        wait (!busy);
        #20;

        // Test receive
        receive = 1;
        // Simulate serial data on Rx (LSB first)
        repeat (8) begin
            #10;
            Rx = $random & 1; // Random bit
        end
        receive = 0;
        #20;

        // End simulation
        $stop;

    end
endmodule

Verilog/waveforms/radio_tb.vcd
$date
	Wed May 21 18:55:24 2025
$end
$version
	Icarus Verilog
$end
$timescale
	1ps
$end
$scope module radio_tb $end
$var wire 8 ! rx_data [7:0] $end
$var wire 1 " busy $end
$var wire 1 # Tx $end
$var reg 1 $ Rx $end
$var reg 1 % clk $end
$var reg 1 & enable $end
$var reg 1 ' receive $end
$var reg 1 ( send $end
$var reg 8 ) tx_data [7:0] $end
$scope module uut $end
$var wire 1 $ Rx $end
$var wire 1 " busy $end
$var wire 1 % clk $end
$var wire 1 & enable $end
$var wire 1 ' receive $end
$var wire 1 ( send $end
$var wire 8 * tx_data [7:0] $end
$var reg 1 # Tx $end
$var reg 3 + rx_bit_cnt [2:0] $end
$var reg 1 , rx_busy $end
$var reg 8 - rx_data [7:0] $end
$var reg 8 . rx_shift_reg [7:0] $end
$var reg 3 / tx_bit_cnt [2:0] $end
$var reg 1 0 tx_busy $end
$var reg 8 1 tx_shift_reg [7:0] $end
$upscope $end
$upscope $end
$enddefinitions $end
$comment Show the parameter values. $end
$dumpall
$end
#0
$dumpvars
b0 1
00
b0 /
b0 .
bx -
0,
b0 +
b0 *
b0 )
0(
0'
0&
0%
0$
x#
0"
bx !
$end
#5000
b0 !
b0 -
0#
1%
#10000
0%
b10101010 )
b10101010 *
1&
#15000
1%
#20000
0%
#25000
1%
#30000
0%
1(
#35000
1"
10
b10101010 1
1%
#40000
0%
0(
#45000
b1 /
b1010101 1
1%
#50000
0%
#55000
b10 /
b101010 1
1#
1%
#60000
0%
#65000
b11 /
b10101 1
0#
1%
#70000
0%
#75000
b100 /
b1010 1
1#
1%
#80000
0%
#85000
b101 /
b101 1
0#
1%
#90000
0%
#95000
b110 /
b10 1
1#
1%
#100000
0%
#105000
b111 /
b1 1
0#
1%
#110000
0%
#115000
0"
00
b0 /
b0 1
1#
1%
#120000
0%
#125000
0#
1%
#130000
0%
#135000
1"
1,
1%
1'
#140000
0%
#145000
b1 +
1%
#150000
0%
#155000
b10 +
b10000000 .
1%
1$
#160000
0%
#165000
b11 +
b11000000 .
1%
#170000
0%
#175000
b100 +
b11100000 .
1%
#180000
0%
#185000
b101 +
b11110000 .
1%
#190000
0%
#195000
b110 +
b11111000 .
1%
#200000
0%
#205000
b111 +
b11111100 .
1%
#210000
0%
#215000
0"
0,
b11111100 !
b11111100 -
b0 +
b1111110 .
1%
0'
0$
